viestikanava.py
celery_viestikanava-0.2.2.dist-info/licenses/Oikeudet.txt
celery_viestikanava-0.2.2.dist-info/METADATA
celery_viestikanava-0.2.2.dist-info/WHEEL
celery_viestikanava-0.2.2.dist-info/historia.json
celery_viestikanava-0.2.2.dist-info/top_level.txt
celery_viestikanava-0.2.2.dist-info/RECORD
