Metadata-Version: 2.4
Name: celery-viestikanava
Version: 0.2.2
Summary: Asynkroninen toteutus Celeryn käyttämiseksi viestinvälitykseen
Author-email: Antti Hautaniemi <antti.hautaniemi@pispalanit.fi>
License-Expression: MIT
Project-URL: Repository, https://github.com/an7oine/celery-viestikanava.git
Requires-Python: >=3.9
License-File: Oikeudet.txt
Requires-Dist: celery
Dynamic: license-file
